{
    "simUI": {
        "msgBox": "simUI/simUI.htm#msgBox",
        "fileDialog": "simUI/simUI.htm#fileDialog",
        "colorDialog": "simUI/simUI.htm#colorDialog",
        "inputDialog": "simUI/simUI.htm#inputDialog",
        "create": "simUI/simUI.htm#create",
        "destroy": "simUI/simUI.htm#destroy",
        "setButtonText": "simUI/simUI.htm#setButtonText",
        "setButtonPressed": "simUI/simUI.htm#setButtonPressed",
        "getSliderValue": "simUI/simUI.htm#getSliderValue",
        "setSliderValue": "simUI/simUI.htm#setSliderValue",
        "getEditValue": "simUI/simUI.htm#getEditValue",
        "setEditValue": "simUI/simUI.htm#setEditValue",
        "getSpinboxValue": "simUI/simUI.htm#getSpinboxValue",
        "setSpinboxValue": "simUI/simUI.htm#setSpinboxValue",
        "getCheckboxValue": "simUI/simUI.htm#getCheckboxValue",
        "setCheckboxValue": "simUI/simUI.htm#setCheckboxValue",
        "getRadiobuttonValue": "simUI/simUI.htm#getRadiobuttonValue",
        "setRadiobuttonValue": "simUI/simUI.htm#setRadiobuttonValue",
        "getLabelText": "simUI/simUI.htm#getLabelText",
        "setLabelText": "simUI/simUI.htm#setLabelText",
        "insertComboboxItem": "simUI/simUI.htm#insertComboboxItem",
        "removeComboboxItem": "simUI/simUI.htm#removeComboboxItem",
        "getComboboxItemCount": "simUI/simUI.htm#getComboboxItemCount",
        "getComboboxItemText": "simUI/simUI.htm#getComboboxItemText",
        "getComboboxItems": "simUI/simUI.htm#getComboboxItems",
        "setComboboxItems": "simUI/simUI.htm#setComboboxItems",
        "getComboboxSelectedIndex": "simUI/simUI.htm#getComboboxSelectedIndex",
        "setComboboxSelectedIndex": "simUI/simUI.htm#setComboboxSelectedIndex",
        "adjustSize": "simUI/simUI.htm#adjustSize",
        "hide": "simUI/simUI.htm#hide",
        "show": "simUI/simUI.htm#show",
        "isVisible": "simUI/simUI.htm#isVisible",
        "getPosition": "simUI/simUI.htm#getPosition",
        "setPosition": "simUI/simUI.htm#setPosition",
        "getSize": "simUI/simUI.htm#getSize",
        "setSize": "simUI/simUI.htm#setSize",
        "getTitle": "simUI/simUI.htm#getTitle",
        "setTitle": "simUI/simUI.htm#setTitle",
        "setWindowEnabled": "simUI/simUI.htm#setWindowEnabled",
        "setImageData": "simUI/simUI.htm#setImageData",
        "setEnabled": "simUI/simUI.htm#setEnabled",
        "getCurrentTab": "simUI/simUI.htm#getCurrentTab",
        "setCurrentTab": "simUI/simUI.htm#setCurrentTab",
        "setStyleSheet": "simUI/simUI.htm#setStyleSheet",
        "getWidgetVisibility": "simUI/simUI.htm#getWidgetVisibility",
        "setWidgetVisibility": "simUI/simUI.htm#setWidgetVisibility",
        "getCurrentEditWidget": "simUI/simUI.htm#getCurrentEditWidget",
        "setCurrentEditWidget": "simUI/simUI.htm#setCurrentEditWidget",
        "replot": "simUI/simUI.htm#replot",
        "addCurve": "simUI/simUI.htm#addCurve",
        "addCurveTimePoints": "simUI/simUI.htm#addCurveTimePoints",
        "addCurveXYPoints": "simUI/simUI.htm#addCurveXYPoints",
        "clearCurve": "simUI/simUI.htm#clearCurve",
        "removeCurve": "simUI/simUI.htm#removeCurve",
        "setPlotRanges": "simUI/simUI.htm#setPlotRanges",
        "setPlotXRange": "simUI/simUI.htm#setPlotXRange",
        "setPlotYRange": "simUI/simUI.htm#setPlotYRange",
        "growPlotRanges": "simUI/simUI.htm#growPlotRanges",
        "growPlotXRange": "simUI/simUI.htm#growPlotXRange",
        "growPlotYRange": "simUI/simUI.htm#growPlotYRange",
        "setPlotLabels": "simUI/simUI.htm#setPlotLabels",
        "setPlotXLabel": "simUI/simUI.htm#setPlotXLabel",
        "setPlotYLabel": "simUI/simUI.htm#setPlotYLabel",
        "rescaleAxes": "simUI/simUI.htm#rescaleAxes",
        "rescaleAxesAll": "simUI/simUI.htm#rescaleAxesAll",
        "setMouseOptions": "simUI/simUI.htm#setMouseOptions",
        "setLegendVisibility": "simUI/simUI.htm#setLegendVisibility",
        "getCurveData": "simUI/simUI.htm#getCurveData",
        "clearTable": "simUI/simUI.htm#clearTable",
        "setRowCount": "simUI/simUI.htm#setRowCount",
        "setColumnCount": "simUI/simUI.htm#setColumnCount",
        "setRowHeaderText": "simUI/simUI.htm#setRowHeaderText",
        "setColumnHeaderText": "simUI/simUI.htm#setColumnHeaderText",
        "setItem": "simUI/simUI.htm#setItem",
        "setItemImage": "simUI/simUI.htm#setItemImage",
        "setItems": "simUI/simUI.htm#setItems",
        "getRowCount": "simUI/simUI.htm#getRowCount",
        "getColumnCount": "simUI/simUI.htm#getColumnCount",
        "getItem": "simUI/simUI.htm#getItem",
        "setItemEditable": "simUI/simUI.htm#setItemEditable",
        "saveState": "simUI/simUI.htm#saveState",
        "restoreState": "simUI/simUI.htm#restoreState",
        "setColumnWidth": "simUI/simUI.htm#setColumnWidth",
        "setRowHeight": "simUI/simUI.htm#setRowHeight",
        "setTableSelection": "simUI/simUI.htm#setTableSelection",
        "setProgress": "simUI/simUI.htm#setProgress",
        "clearTree": "simUI/simUI.htm#clearTree",
        "addTreeItem": "simUI/simUI.htm#addTreeItem",
        "updateTreeItemText": "simUI/simUI.htm#updateTreeItemText",
        "updateTreeItemParent": "simUI/simUI.htm#updateTreeItemParent",
        "removeTreeItem": "simUI/simUI.htm#removeTreeItem",
        "setTreeSelection": "simUI/simUI.htm#setTreeSelection",
        "expandAll": "simUI/simUI.htm#expandAll",
        "collapseAll": "simUI/simUI.htm#collapseAll",
        "expandToDepth": "simUI/simUI.htm#expandToDepth",
        "setText": "simUI/simUI.htm#setText",
        "appendText": "simUI/simUI.htm#appendText",
        "setUrl": "simUI/simUI.htm#setUrl",
        "addScene3DNode": "simUI/simUI.htm#addScene3DNode",
        "removeScene3DNode": "simUI/simUI.htm#removeScene3DNode",
        "setScene3DNodeEnabled": "simUI/simUI.htm#setScene3DNodeEnabled",
        "setScene3DNodeIntParam": "simUI/simUI.htm#setScene3DNodeIntParam",
        "setScene3DNodeFloatParam": "simUI/simUI.htm#setScene3DNodeFloatParam",
        "setScene3DNodeStringParam": "simUI/simUI.htm#setScene3DNodeStringParam",
        "setScene3DNodeVector2Param": "simUI/simUI.htm#setScene3DNodeVector2Param",
        "setScene3DNodeVector3Param": "simUI/simUI.htm#setScene3DNodeVector3Param",
        "setScene3DNodeVector4Param": "simUI/simUI.htm#setScene3DNodeVector4Param",
        "svgLoadFile": "simUI/simUI.htm#svgLoadFile",
        "svgLoadData": "simUI/simUI.htm#svgLoadData",
        "supportedImageFormats": "simUI/simUI.htm#supportedImageFormats",
        "getKeyboardModifiers": "simUI/simUI.htm#getKeyboardModifiers",
        "qtVersion": "simUI/simUI.htm#qtVersion",
        "setClipboardText": "simUI/simUI.htm#setClipboardText",
        "setProperties": "simUI/simUI.htm#setProperties",
        "setPropertiesRows": "simUI/simUI.htm#setPropertiesRows",
        "setPropertiesSelection": "simUI/simUI.htm#setPropertiesSelection",
        "setPropertiesContextMenu": "simUI/simUI.htm#setPropertiesContextMenu",
        "setPropertiesState": "simUI/simUI.htm#setPropertiesState",
        "getPropertiesState": "simUI/simUI.htm#getPropertiesState",
        "bannerCreate": "simUI/simUI.htm#bannerCreate",
        "bannerDestroy": "simUI/simUI.htm#bannerDestroy",
        "insertTableRow": "simUI/simUI.htm#insertTableRow",
        "removeTableRow": "simUI/simUI.htm#removeTableRow",
        "insertTableColumn": "simUI/simUI.htm#insertTableColumn",
        "removeTableColumn": "simUI/simUI.htm#removeTableColumn",
        "setScene3DNodeParam": "simUI/simUI.htm#setScene3DNodeParam",
        "msgbox_type": "simUI/simUI.htm#enum:msgbox_type",
        "msgbox_type.info": "simUI/simUI.htm#enum:msgbox_type",
        "msgbox_type.question": "simUI/simUI.htm#enum:msgbox_type",
        "msgbox_type.warning": "simUI/simUI.htm#enum:msgbox_type",
        "msgbox_type.critical": "simUI/simUI.htm#enum:msgbox_type",
        "msgbox_buttons": "simUI/simUI.htm#enum:msgbox_buttons",
        "msgbox_buttons.ok": "simUI/simUI.htm#enum:msgbox_buttons",
        "msgbox_buttons.yesno": "simUI/simUI.htm#enum:msgbox_buttons",
        "msgbox_buttons.yesnocancel": "simUI/simUI.htm#enum:msgbox_buttons",
        "msgbox_buttons.okcancel": "simUI/simUI.htm#enum:msgbox_buttons",
        "msgbox_result": "simUI/simUI.htm#enum:msgbox_result",
        "msgbox_result.cancel": "simUI/simUI.htm#enum:msgbox_result",
        "msgbox_result.no": "simUI/simUI.htm#enum:msgbox_result",
        "msgbox_result.yes": "simUI/simUI.htm#enum:msgbox_result",
        "msgbox_result.ok": "simUI/simUI.htm#enum:msgbox_result",
        "filedialog_type": "simUI/simUI.htm#enum:filedialog_type",
        "filedialog_type.load": "simUI/simUI.htm#enum:filedialog_type",
        "filedialog_type.load_multiple": "simUI/simUI.htm#enum:filedialog_type",
        "filedialog_type.save": "simUI/simUI.htm#enum:filedialog_type",
        "filedialog_type.folder": "simUI/simUI.htm#enum:filedialog_type",
        "curve_type": "simUI/simUI.htm#enum:curve_type",
        "curve_type.time": "simUI/simUI.htm#enum:curve_type",
        "curve_type.xy": "simUI/simUI.htm#enum:curve_type",
        "curve_style": "simUI/simUI.htm#enum:curve_style",
        "curve_style.scatter": "simUI/simUI.htm#enum:curve_style",
        "curve_style.line": "simUI/simUI.htm#enum:curve_style",
        "curve_style.line_and_scatter": "simUI/simUI.htm#enum:curve_style",
        "curve_style.step_left": "simUI/simUI.htm#enum:curve_style",
        "curve_style.step_center": "simUI/simUI.htm#enum:curve_style",
        "curve_style.step_right": "simUI/simUI.htm#enum:curve_style",
        "curve_style.impulse": "simUI/simUI.htm#enum:curve_style",
        "curve_scatter_shape": "simUI/simUI.htm#enum:curve_scatter_shape",
        "curve_scatter_shape.none": "simUI/simUI.htm#enum:curve_scatter_shape",
        "curve_scatter_shape.dot": "simUI/simUI.htm#enum:curve_scatter_shape",
        "curve_scatter_shape.cross": "simUI/simUI.htm#enum:curve_scatter_shape",
        "curve_scatter_shape.plus": "simUI/simUI.htm#enum:curve_scatter_shape",
        "curve_scatter_shape.circle": "simUI/simUI.htm#enum:curve_scatter_shape",
        "curve_scatter_shape.disc": "simUI/simUI.htm#enum:curve_scatter_shape",
        "curve_scatter_shape.square": "simUI/simUI.htm#enum:curve_scatter_shape",
        "curve_scatter_shape.diamond": "simUI/simUI.htm#enum:curve_scatter_shape",
        "curve_scatter_shape.star": "simUI/simUI.htm#enum:curve_scatter_shape",
        "curve_scatter_shape.triangle": "simUI/simUI.htm#enum:curve_scatter_shape",
        "curve_scatter_shape.triangle_inverted": "simUI/simUI.htm#enum:curve_scatter_shape",
        "curve_scatter_shape.cross_square": "simUI/simUI.htm#enum:curve_scatter_shape",
        "curve_scatter_shape.plus_square": "simUI/simUI.htm#enum:curve_scatter_shape",
        "curve_scatter_shape.cross_circle": "simUI/simUI.htm#enum:curve_scatter_shape",
        "curve_scatter_shape.plus_circle": "simUI/simUI.htm#enum:curve_scatter_shape",
        "curve_scatter_shape.peace": "simUI/simUI.htm#enum:curve_scatter_shape",
        "line_style": "simUI/simUI.htm#enum:line_style",
        "line_style.solid": "simUI/simUI.htm#enum:line_style",
        "line_style.dotted": "simUI/simUI.htm#enum:line_style",
        "line_style.dashed": "simUI/simUI.htm#enum:line_style",
        "scene3d_node_type": "simUI/simUI.htm#enum:scene3d_node_type",
        "scene3d_node_type.entity": "simUI/simUI.htm#enum:scene3d_node_type",
        "scene3d_node_type.transform": "simUI/simUI.htm#enum:scene3d_node_type",
        "scene3d_node_type.camera": "simUI/simUI.htm#enum:scene3d_node_type",
        "scene3d_node_type.camera_controller_first_person": "simUI/simUI.htm#enum:scene3d_node_type",
        "scene3d_node_type.camera_controller_orbit": "simUI/simUI.htm#enum:scene3d_node_type",
        "scene3d_node_type.light_point": "simUI/simUI.htm#enum:scene3d_node_type",
        "scene3d_node_type.light_directional": "simUI/simUI.htm#enum:scene3d_node_type",
        "scene3d_node_type.light_spot": "simUI/simUI.htm#enum:scene3d_node_type",
        "scene3d_node_type.mesh_cuboid": "simUI/simUI.htm#enum:scene3d_node_type",
        "scene3d_node_type.mesh_torus": "simUI/simUI.htm#enum:scene3d_node_type",
        "scene3d_node_type.mesh_cone": "simUI/simUI.htm#enum:scene3d_node_type",
        "scene3d_node_type.mesh_cylinder": "simUI/simUI.htm#enum:scene3d_node_type",
        "scene3d_node_type.mesh_plane": "simUI/simUI.htm#enum:scene3d_node_type",
        "scene3d_node_type.mesh_sphere": "simUI/simUI.htm#enum:scene3d_node_type",
        "scene3d_node_type.mesh": "simUI/simUI.htm#enum:scene3d_node_type",
        "scene3d_node_type.material_phong": "simUI/simUI.htm#enum:scene3d_node_type",
        "scene3d_node_type.material_gooch": "simUI/simUI.htm#enum:scene3d_node_type",
        "scene3d_node_type.material_texture": "simUI/simUI.htm#enum:scene3d_node_type",
        "scene3d_node_type.material_diffuse_map": "simUI/simUI.htm#enum:scene3d_node_type",
        "scene3d_node_type.texture2d": "simUI/simUI.htm#enum:scene3d_node_type",
        "scene3d_node_type.texture_image": "simUI/simUI.htm#enum:scene3d_node_type",
        "scene3d_node_type.object_picker": "simUI/simUI.htm#enum:scene3d_node_type",
        "mouse": "simUI/simUI.htm#enum:mouse",
        "mouse.left_button_down": "simUI/simUI.htm#enum:mouse",
        "mouse.left_button_up": "simUI/simUI.htm#enum:mouse",
        "mouse.move": "simUI/simUI.htm#enum:mouse",
        "onclickCallback": "simUI/simUI.htm#scriptfun:onclickCallback",
        "onLinkActivatedCallback": "simUI/simUI.htm#scriptfun:onLinkActivatedCallback",
        "onchangeIntCallback": "simUI/simUI.htm#scriptfun:onchangeIntCallback",
        "onchangeDoubleCallback": "simUI/simUI.htm#scriptfun:onchangeDoubleCallback",
        "onchangeStringCallback": "simUI/simUI.htm#scriptfun:onchangeStringCallback",
        "oneditingfinishedCallback": "simUI/simUI.htm#scriptfun:oneditingfinishedCallback",
        "oncloseCallback": "simUI/simUI.htm#scriptfun:oncloseCallback",
        "onPlottableClickCallback": "simUI/simUI.htm#scriptfun:onPlottableClickCallback",
        "onLegendClickCallback": "simUI/simUI.htm#scriptfun:onLegendClickCallback",
        "onCellActivateCallback": "simUI/simUI.htm#scriptfun:onCellActivateCallback",
        "onTableSelectionChangeCallback": "simUI/simUI.htm#scriptfun:onTableSelectionChangeCallback",
        "onPropertiesSelectionChangeCallback": "simUI/simUI.htm#scriptfun:onPropertiesSelectionChangeCallback",
        "onPropertiesDoubleClickCallback": "simUI/simUI.htm#scriptfun:onPropertiesDoubleClickCallback",
        "onPropertiesContextMenuTriggeredCallback": "simUI/simUI.htm#scriptfun:onPropertiesContextMenuTriggeredCallback",
        "onPropertiesPropertyEditCallback": "simUI/simUI.htm#scriptfun:onPropertiesPropertyEditCallback",
        "onTreeSelectionChangeCallback": "simUI/simUI.htm#scriptfun:onTreeSelectionChangeCallback",
        "onMouseEventCallback": "simUI/simUI.htm#scriptfun:onMouseEventCallback",
        "onKeyPressCallback": "simUI/simUI.htm#scriptfun:onKeyPressCallback",
        "onScene3DObjectClickCallback": "simUI/simUI.htm#scriptfun:onScene3DObjectClickCallback",
        "onBannerButtonClickCallback": "simUI/simUI.htm#scriptfun:onBannerButtonClickCallback",
        "curve_options": "simUI/simUI.htm#struct:curve_options",
        "keyboard_modifiers": "simUI/simUI.htm#struct:keyboard_modifiers"
    }
}